anotegenerate/__init__.py
anotegenerate/core.py
anote_generate-0.3.dist-info/METADATA
anote_generate-0.3.dist-info/WHEEL
anote_generate-0.3.dist-info/top_level.txt
anote_generate-0.3.dist-info/RECORD
