Metadata-Version: 2.4
Name: anote-generate
Version: 0.3
Summary: An SDK for generating synthetic data with the Anote API
Home-page: https://github.com/nv78/Anote
Author: Natan Vidra
Author-email: nvidra@anote.ai
License: MIT
Requires-Dist: annotated-types==0.7.0
Requires-Dist: anyio==4.9.0
Requires-Dist: blinker==1.9.0
Requires-Dist: blis==1.3.0
Requires-Dist: cachetools==5.5.2
Requires-Dist: catalogue==2.0.10
Requires-Dist: certifi==2025.6.15
Requires-Dist: charset-normalizer==3.4.2
Requires-Dist: click==8.2.1
Requires-Dist: cloudpathlib==0.21.1
Requires-Dist: colorama==0.4.6
Requires-Dist: confection==0.1.5
Requires-Dist: contourpy==1.3.2
Requires-Dist: cycler==0.12.1
Requires-Dist: cymem==2.0.11
Requires-Dist: distro==1.9.0
Requires-Dist: dotenv==0.9.9
Requires-Dist: Faker==37.4.2
Requires-Dist: fastapi==0.115.14
Requires-Dist: filelock==3.18.0
Requires-Dist: Flask==3.1.1
Requires-Dist: fonttools==4.58.5
Requires-Dist: fsspec==2025.5.1
Requires-Dist: google-auth==2.40.3
Requires-Dist: google-genai==1.24.0
Requires-Dist: h11==0.16.0
Requires-Dist: httpcore==1.0.9
Requires-Dist: httpx==0.28.1
Requires-Dist: idna==3.10
Requires-Dist: itsdangerous==2.2.0
Requires-Dist: Jinja2==3.1.6
Requires-Dist: jiter==0.10.0
Requires-Dist: joblib==1.5.1
Requires-Dist: kiwisolver==1.4.8
Requires-Dist: langcodes==3.5.0
Requires-Dist: language_data==1.3.0
Requires-Dist: marisa-trie==1.2.1
Requires-Dist: markdown-it-py==3.0.0
Requires-Dist: MarkupSafe==3.0.2
Requires-Dist: matplotlib==3.10.3
Requires-Dist: mdurl==0.1.2
Requires-Dist: mpmath==1.3.0
Requires-Dist: murmurhash==1.0.13
Requires-Dist: nest-asyncio==1.6.0
Requires-Dist: networkx==3.5
Requires-Dist: numpy==2.2.6
Requires-Dist: openai==1.93.0
Requires-Dist: opencv-python==4.12.0.88
Requires-Dist: packaging==25.0
Requires-Dist: pandas==2.3.0
Requires-Dist: pillow==11.3.0
Requires-Dist: preshed==3.0.10
Requires-Dist: psutil==7.0.0
Requires-Dist: py-cpuinfo==9.0.0
Requires-Dist: pyasn1==0.6.1
Requires-Dist: pyasn1_modules==0.4.2
Requires-Dist: pydantic==2.11.7
Requires-Dist: pydantic_core==2.33.2
Requires-Dist: Pygments==2.19.2
Requires-Dist: PyJWT==2.10.1
Requires-Dist: pyparsing==3.2.3
Requires-Dist: python-dateutil==2.9.0.post0
Requires-Dist: python-dotenv==1.1.1
Requires-Dist: pytz==2025.2
Requires-Dist: PyYAML==6.0.2
Requires-Dist: requests==2.32.4
Requires-Dist: rich==14.0.0
Requires-Dist: rsa==4.9.1
Requires-Dist: scikit-learn==1.7.1
Requires-Dist: scipy==1.16.0
Requires-Dist: setuptools==80.9.0
Requires-Dist: shellingham==1.5.4
Requires-Dist: six==1.17.0
Requires-Dist: smart_open==7.3.0.post1
Requires-Dist: sniffio==1.3.1
Requires-Dist: spacy==3.8.7
Requires-Dist: spacy-legacy==3.0.12
Requires-Dist: spacy-loggers==1.0.5
Requires-Dist: srsly==2.5.1
Requires-Dist: starlette==0.46.2
Requires-Dist: sympy==1.14.0
Requires-Dist: tenacity==8.5.0
Requires-Dist: thinc==8.3.6
Requires-Dist: threadpoolctl==3.6.0
Requires-Dist: torch==2.7.1
Requires-Dist: torchvision==0.22.1
Requires-Dist: tqdm==4.67.1
Requires-Dist: typer==0.16.0
Requires-Dist: typing-inspection==0.4.1
Requires-Dist: typing_extensions==4.14.0
Requires-Dist: tzdata==2025.2
Requires-Dist: ultralytics==8.3.166
Requires-Dist: ultralytics-thop==2.0.14
Requires-Dist: urllib3==2.5.0
Requires-Dist: uvicorn==0.35.0
Requires-Dist: wasabi==1.1.3
Requires-Dist: weasel==0.4.1
Requires-Dist: websockets==15.0.1
Requires-Dist: Werkzeug==3.1.3
Requires-Dist: wrapt==1.17.2
Dynamic: author
Dynamic: author-email
Dynamic: home-page
Dynamic: license
Dynamic: requires-dist
Dynamic: summary
